{"data": [{"word": "#UFC289", "value": 232836}, {"word": "Nunes", "value": 141313}, {"word": "Charles", "value": 180226}, {"word": "#TaylorLopez", "value": 33710}, {"word": "#QueenRadio", "value": 13458}, {"word": "Josh Taylor", "value": 21770}, {"word": "#BarbieWorld", "value": 23167}, {"word": "Dariush", "value": 68966}, {"word": "Peña", "value": 118871}, {"word": "#WakeoneTreatRickyBetter", "value": 119718}, {"word": "ZEROBASEONE IS 9", "value": 113058}, {"word": "Islam", "value": 77767}, {"word": "nayeon", "value": 38751}, {"word": "jihyo", "value": 51463}, {"word": "Volk", "value": 15418}, {"word": "jeongyeon", "value": 22067}, {"word": "Leave Children Alone", "value": 22542}, {"word": "Omaha", "value": 12623}, {"word": "The Takeover", "value": 15514}, {"word": "Home Depot", "value": 11397}, {"word": "Waffle House", "value": 25661}, {"word": "Francois", "value": 16560}, {"word": "#RICKY_IS_ZB1", "value": 119982}], "url_map": {"#UFC289": "http://twitter.com/search?q=%23UFC289", "Nunes": "http://twitter.com/search?q=Nunes", "Charles": "http://twitter.com/search?q=Charles", "#TaylorLopez": "http://twitter.com/search?q=%23TaylorLopez", "#QueenRadio": "http://twitter.com/search?q=%23QueenRadio", "Josh Taylor": "http://twitter.com/search?q=%22Josh+Taylor%22", "#BarbieWorld": "http://twitter.com/search?q=%23BarbieWorld", "Dariush": "http://twitter.com/search?q=Dariush", "Peña": "http://twitter.com/search?q=Pe%C3%B1a", "#WakeoneTreatRickyBetter": "http://twitter.com/search?q=%23WakeoneTreatRickyBetter", "ZEROBASEONE IS 9": "http://twitter.com/search?q=%22ZEROBASEONE+IS+9%22", "Islam": "http://twitter.com/search?q=Islam", "nayeon": "http://twitter.com/search?q=nayeon", "jihyo": "http://twitter.com/search?q=jihyo", "Volk": "http://twitter.com/search?q=Volk", "jeongyeon": "http://twitter.com/search?q=jeongyeon", "Leave Children Alone": "http://twitter.com/search?q=%22Leave+Children+Alone%22", "Omaha": "http://twitter.com/search?q=Omaha", "The Takeover": "http://twitter.com/search?q=%22The+Takeover%22", "Home Depot": "http://twitter.com/search?q=%22Home+Depot%22", "Waffle House": "http://twitter.com/search?q=%22Waffle+House%22", "Francois": "http://twitter.com/search?q=Francois", "#RICKY_IS_ZB1": "http://twitter.com/search?q=%23RICKY_IS_ZB1"}, "title": "Pop Tags", "topic": "USA"}