{"data": [{"word": "Foden", "value": 101000}, {"word": "Arsenal", "value": 411000}, {"word": "Caicedo", "value": 19000}, {"word": "West Ham", "value": 58000}, {"word": "Lando", "value": 44000}, {"word": "Man City", "value": 68000}, {"word": "#IMOLAGP", "value": 153000}, {"word": "Morehouse", "value": 19000}, {"word": "#ARSEVE", "value": 12000}, {"word": "Raisi", "value": 83000}, {"word": "Manchester City", "value": 60000}, {"word": "Good Sunday", "value": 57000}, {"word": "Doku", "value": 11000}, {"word": "Klopp", "value": 167000}, {"word": "Saka", "value": 56000}, {"word": "JEONGHAN", "value": 239000}, {"word": "Verstappen", "value": 54000}, {"word": "Gunners", "value": 18000}, {"word": "BIGHIT TREAT TXT BETTER", "value": 63000}, {"word": "BIGHIT STOP MISTREATING TXT", "value": 62000}, {"word": "The Warmest Gift of Spring", "value": 28000}, {"word": "McLaren", "value": 36000}, {"word": "Jurgen", "value": 84000}, {"word": "Emirates", "value": 24000}, {"word": "Farmer", "value": 49000}, {"word": "You'll Never Walk Alone", "value": 19000}, {"word": "Malcolm X", "value": 10000}, {"word": "Anfield", "value": 43000}, {"word": "Norris", "value": 23000}, {"word": "Everton", "value": 53000}, {"word": "Blessed Sunday", "value": 13000}, {"word": "Checo", "value": 17000}, {"word": "Twitter X", "value": 1120000}, {"word": "OPEN YOUR EYES", "value": 22000}, {"word": "Portuguese", "value": 16000}, {"word": "Tannie", "value": 23000}, {"word": "Sainz", "value": 15000}, {"word": "#ImolaGP", "value": 124000}, {"word": "#MSI2024", "value": 26000}, {"word": "tannie", "value": 20000}, {"word": "Taxes", "value": 81000}, {"word": "Alice Stewart", "value": 24000}, {"word": "The 2020", "value": 104000}, {"word": "Portugal", "value": 152000}, {"word": "Paint", "value": 48000}, {"word": "Chivas", "value": 76000}, {"word": "Drug", "value": 128000}, {"word": "yeonjun", "value": 54000}, {"word": "Slug", "value": 10000}, {"word": "Wuthering Waves", "value": 22000}], "url_map": {"Foden": "https://twitter.com/search?q=Foden", "Arsenal": "https://twitter.com/search?q=Arsenal", "Caicedo": "https://twitter.com/search?q=Caicedo", "West Ham": "https://twitter.com/search?q=%22West+Ham%22", "Lando": "https://twitter.com/search?q=Lando", "Man City": "https://twitter.com/search?q=%22Man+City%22", "#IMOLAGP": "https://twitter.com/search?q=%23IMOLAGP", "Morehouse": "https://twitter.com/search?q=Morehouse", "#ARSEVE": "https://twitter.com/search?q=%23ARSEVE", "Raisi": "https://twitter.com/search?q=Raisi", "Manchester City": "https://twitter.com/search?q=%22Manchester+City%22", "Good Sunday": "https://twitter.com/search?q=%22Good+Sunday%22", "Doku": "https://twitter.com/search?q=Doku", "Klopp": "https://twitter.com/search?q=Klopp", "Saka": "https://twitter.com/search?q=Saka", "JEONGHAN": "https://twitter.com/search?q=JEONGHAN", "Verstappen": "https://twitter.com/search?q=Verstappen", "Gunners": "https://twitter.com/search?q=Gunners", "BIGHIT TREAT TXT BETTER": "https://twitter.com/search?q=%22BIGHIT+TREAT+TXT+BETTER%22", "BIGHIT STOP MISTREATING TXT": "https://twitter.com/search?q=%22BIGHIT+STOP+MISTREATING+TXT%22", "The Warmest Gift of Spring": "https://twitter.com/search?q=%22The+Warmest+Gift+of+Spring%22", "McLaren": "https://twitter.com/search?q=McLaren", "Jurgen": "https://twitter.com/search?q=Jurgen", "Emirates": "https://twitter.com/search?q=Emirates", "Farmer": "https://twitter.com/search?q=Farmer", "You'll Never Walk Alone": "https://twitter.com/search?q=%22You%27ll+Never+Walk+Alone%22", "Malcolm X": "https://twitter.com/search?q=%22Malcolm+X%22", "Anfield": "https://twitter.com/search?q=Anfield", "Norris": "https://twitter.com/search?q=Norris", "Everton": "https://twitter.com/search?q=Everton", "Blessed Sunday": "https://twitter.com/search?q=%22Blessed+Sunday%22", "Checo": "https://twitter.com/search?q=Checo", "Twitter X": "https://twitter.com/search?q=%22Twitter+X%22", "OPEN YOUR EYES": "https://twitter.com/search?q=%22OPEN+YOUR+EYES%22", "Portuguese": "https://twitter.com/search?q=Portuguese", "Tannie": "https://twitter.com/search?q=Tannie", "Sainz": "https://twitter.com/search?q=Sainz", "#ImolaGP": "https://twitter.com/search?q=%23ImolaGP", "#MSI2024": "https://twitter.com/search?q=%23MSI2024", "tannie": "https://twitter.com/search?q=tannie", "Taxes": "https://twitter.com/search?q=Taxes", "Alice Stewart": "https://twitter.com/search?q=%22Alice+Stewart%22", "The 2020": "https://twitter.com/search?q=%22The+2020%22", "Portugal": "https://twitter.com/search?q=Portugal", "Paint": "https://twitter.com/search?q=Paint", "Chivas": "https://twitter.com/search?q=Chivas", "Drug": "https://twitter.com/search?q=Drug", "yeonjun": "https://twitter.com/search?q=yeonjun", "Slug": "https://twitter.com/search?q=Slug", "Wuthering Waves": "https://twitter.com/search?q=%22Wuthering+Waves%22"}, "title": "Pop Tags", "topic": "USA"}