{"data": [{"word": "Putin", "value": 14}, {"word": "Moscow", "value": 616100}, {"word": "#AgustD_SUGA_Tour_in_Seoul", "value": 176500}, {"word": "Good Saturday", "value": 27600}, {"word": "Min Yoongi", "value": 115100}, {"word": "st. petersburg", "value": 41500}, {"word": "Tony Montana", "value": 78600}, {"word": "rostov", "value": 658000}, {"word": "Belarus", "value": 58400}, {"word": "WWIII", "value": 10100}, {"word": "Prighozin", "value": 23100}, {"word": "Voronezh", "value": 184600}, {"word": "Kremlin", "value": 228200}, {"word": "Dobbs", "value": 38200}, {"word": "Ucrania", "value": 90300}, {"word": "Lipetsk", "value": 37500}, {"word": "The CIA", "value": 74500}, {"word": "Jhope", "value": 42200}, {"word": "Moscú", "value": 101800}, {"word": "Amygdala", "value": 17300}, {"word": "lukashenko", "value": 46000}, {"word": "Life goes on", "value": 35400}, {"word": "The Last", "value": 825300}, {"word": "THE SUIT", "value": 48900}, {"word": "God is Good", "value": 31100}, {"word": "Kadyrov", "value": 34800}, {"word": "Kiev", "value": 34000}, {"word": "but the lord", "value": 13100}], "url_map": {"Putin": "http://twitter.com/search?q=Putin", "Moscow": "http://twitter.com/search?q=Moscow", "#AgustD_SUGA_Tour_in_Seoul": "http://twitter.com/search?q=%23AgustD_SUGA_Tour_in_Seoul", "Good Saturday": "http://twitter.com/search?q=Good%20Saturday", "Min Yoongi": "http://twitter.com/search?q=Min%20Yoongi", "st. petersburg": "http://twitter.com/search?q=st.%20petersburg", "Tony Montana": "http://twitter.com/search?q=Tony%20Montana", "rostov": "http://twitter.com/search?q=rostov", "Belarus": "http://twitter.com/search?q=Belarus", "WWIII": "http://twitter.com/search?q=WWIII", "Prighozin": "http://twitter.com/search?q=Prighozin", "Voronezh": "http://twitter.com/search?q=Voronezh", "Kremlin": "http://twitter.com/search?q=Kremlin", "Dobbs": "http://twitter.com/search?q=Dobbs", "Ucrania": "http://twitter.com/search?q=Ucrania", "Lipetsk": "http://twitter.com/search?q=Lipetsk", "The CIA": "http://twitter.com/search?q=The%20CIA", "Jhope": "http://twitter.com/search?q=Jhope", "Moscú": "http://twitter.com/search?q=Mosc%C3%BA", "Amygdala": "http://twitter.com/search?q=Amygdala", "lukashenko": "http://twitter.com/search?q=lukashenko", "Life goes on": "http://twitter.com/search?q=Life%20goes%20on", "The Last": "http://twitter.com/search?q=The%20Last", "THE SUIT": "http://twitter.com/search?q=THE%20SUIT", "God is Good": "http://twitter.com/search?q=God%20is%20Good", "Kadyrov": "http://twitter.com/search?q=Kadyrov", "Kiev": "http://twitter.com/search?q=Kiev", "but the lord": "http://twitter.com/search?q=but%20the%20lord"}, "title": "Pop Tags", "topic": "USA"}