{"data": [{"word": "Lebron", "value": 560755}, {"word": "Lebron", "value": 560755}, {"word": "Lebron", "value": 560755}, {"word": "Jokic", "value": 211772}, {"word": "U-Haul", "value": 10383}, {"word": "Good Tuesday", "value": 20929}, {"word": "#Jimin1BonSpotify", "value": 84164}, {"word": "Kobe", "value": 47392}, {"word": "Tristan Thompson", "value": 32703}, {"word": "#LakeShow", "value": 20103}, {"word": "Kyrie", "value": 31472}, {"word": "Joker", "value": 78362}, {"word": "Anthony Davis", "value": 38329}, {"word": "HBO Max", "value": 18310}, {"word": "Finals", "value": 215397}, {"word": "Swept", "value": 120569}, {"word": "Aaron Gordon", "value": 13149}, {"word": "He's 38", "value": 11396}, {"word": "Pong", "value": 10981}, {"word": "sam levinson", "value": 18780}, {"word": "Lindsay", "value": 19451}, {"word": "The Dodgers", "value": 36836}, {"word": "The Idol", "value": 319380}, {"word": "$RFD", "value": 2293730}], "url_map": {"Lebron": "http://twitter.com/search?q=Lebron", "Jokic": "http://twitter.com/search?q=Jokic", "U-Haul": "http://twitter.com/search?q=U-Haul", "Good Tuesday": "http://twitter.com/search?q=%22Good+Tuesday%22", "#Jimin1BonSpotify": "http://twitter.com/search?q=%23Jimin1BonSpotify", "Kobe": "http://twitter.com/search?q=Kobe", "Tristan Thompson": "http://twitter.com/search?q=%22Tristan+Thompson%22", "#LakeShow": "http://twitter.com/search?q=%23LakeShow", "Kyrie": "http://twitter.com/search?q=Kyrie", "Joker": "http://twitter.com/search?q=Joker", "Anthony Davis": "http://twitter.com/search?q=%22Anthony+Davis%22", "HBO Max": "http://twitter.com/search?q=%22HBO+Max%22", "Finals": "http://twitter.com/search?q=Finals", "Swept": "http://twitter.com/search?q=Swept", "Aaron Gordon": "http://twitter.com/search?q=%22Aaron+Gordon%22", "He's 38": "http://twitter.com/search?q=%22He%27s+38%22", "Pong": "http://twitter.com/search?q=Pong", "sam levinson": "http://twitter.com/search?q=%22sam+levinson%22", "Lindsay": "http://twitter.com/search?q=Lindsay", "The Dodgers": "http://twitter.com/search?q=%22The+Dodgers%22", "The Idol": "http://twitter.com/search?q=%22The+Idol%22", "$RFD": "http://twitter.com/search?q=%24RFD"}, "title": "Pop Tags", "topic": "USA"}