{"data": [{"word": "#UFC290", "value": 214000}, {"word": "Robbie Lawler", "value": 23700}, {"word": "Bo Nickal", "value": 10300}, {"word": "#AEWCollision", "value": 30600}, {"word": "Turner", "value": 27600}, {"word": "Jonah Hill", "value": 49900}, {"word": "Elly De La Cruz", "value": 32900}, {"word": "De Los Santos", "value": 10300}, {"word": "Punk", "value": 51600}, {"word": "Cámara", "value": 56600}, {"word": "Volkanovski vs Rodriguez", "value": 84600}, {"word": "Rays", "value": 11600}, {"word": "Bilal", "value": 12000}, {"word": "Chivas", "value": 20400}, {"word": "Benghazi", "value": 22300}], "url_map": {"#UFC290": "http://twitter.com/search?q=%23UFC290", "Robbie Lawler": "http://twitter.com/search?q=Robbie%20Lawler", "Bo Nickal": "http://twitter.com/search?q=Bo%20Nickal", "#AEWCollision": "http://twitter.com/search?q=%23AEWCollision", "Turner": "http://twitter.com/search?q=Turner", "Jonah Hill": "http://twitter.com/search?q=Jonah%20Hill", "Elly De La Cruz": "http://twitter.com/search?q=Elly%20De%20La%20Cruz", "De Los Santos": "http://twitter.com/search?q=De%20Los%20Santos", "Punk": "http://twitter.com/search?q=Punk", "Cámara": "http://twitter.com/search?q=C%C3%A1mara", "Volkanovski vs Rodriguez": "http://twitter.com/search?q=Volkanovski%20vs%20Rodriguez", "Rays": "http://twitter.com/search?q=Rays", "Bilal": "http://twitter.com/search?q=Bilal", "Chivas": "http://twitter.com/search?q=Chivas", "Benghazi": "http://twitter.com/search?q=Benghazi"}, "title": "Pop Tags", "topic": "USA"}