{"data": [{"word": "#FursuitFriday", "value": 15900}, {"word": "#WorldChocolateDay", "value": 13000}, {"word": "Pulisic", "value": 34500}, {"word": "URGENT MESSAGE", "value": 14700}, {"word": "Taylor Swift", "value": 513500}, {"word": "Ringo", "value": 34600}, {"word": "Taemin", "value": 94400}, {"word": "Jungkook", "value": 16}, {"word": "Cardi", "value": 97000}, {"word": "Tulsa Race Massacre", "value": 11100}, {"word": "Sabrina", "value": 21900}, {"word": "AC Milan", "value": 24800}, {"word": "Tsitsipas", "value": 15900}, {"word": "A'ja", "value": 299500}, {"word": "Andy Murray", "value": 23100}, {"word": "Casey DeSantis", "value": 27000}, {"word": "Gambino", "value": 14600}, {"word": "My Adventures with Superman", "value": 13600}, {"word": "Trump White House", "value": 37700}, {"word": "Haechan", "value": 314100}, {"word": "Edwin", "value": 58100}, {"word": "Rosalynn Carter", "value": 13000}, {"word": "Good Friday", "value": 67800}, {"word": "Michael Jackson", "value": 29800}], "url_map": {"#FursuitFriday": "http://twitter.com/search?q=%23FursuitFriday", "#WorldChocolateDay": "http://twitter.com/search?q=%23WorldChocolateDay", "Pulisic": "http://twitter.com/search?q=Pulisic", "URGENT MESSAGE": "http://twitter.com/search?q=URGENT%20MESSAGE", "Taylor Swift": "http://twitter.com/search?q=Taylor%20Swift", "Ringo": "http://twitter.com/search?q=Ringo", "Taemin": "http://twitter.com/search?q=Taemin", "Jungkook": "http://twitter.com/search?q=Jungkook", "Cardi": "http://twitter.com/search?q=Cardi", "Tulsa Race Massacre": "http://twitter.com/search?q=Tulsa%20Race%20Massacre", "Sabrina": "http://twitter.com/search?q=Sabrina", "AC Milan": "http://twitter.com/search?q=AC%20Milan", "Tsitsipas": "http://twitter.com/search?q=Tsitsipas", "A'ja": "http://twitter.com/search?q=A'ja", "Andy Murray": "http://twitter.com/search?q=Andy%20Murray", "Casey DeSantis": "http://twitter.com/search?q=Casey%20DeSantis", "Gambino": "http://twitter.com/search?q=Gambino", "My Adventures with Superman": "http://twitter.com/search?q=My%20Adventures%20with%20Superman", "Trump White House": "http://twitter.com/search?q=Trump%20White%20House", "Haechan": "http://twitter.com/search?q=Haechan", "Edwin": "http://twitter.com/search?q=Edwin", "Rosalynn Carter": "http://twitter.com/search?q=Rosalynn%20Carter", "Good Friday": "http://twitter.com/search?q=Good%20Friday", "Michael Jackson": "http://twitter.com/search?q=Michael%20Jackson"}, "title": "Pop Tags", "topic": "USA"}