{"data": [{"word": "Happy 4th", "value": 905500}, {"word": "Bol Bol", "value": 69400}, {"word": "White House", "value": 299100}, {"word": "Guatemala", "value": 53500}, {"word": "Jerry", "value": 33500}, {"word": "Fourth of July", "value": 258500}, {"word": "Mingyu", "value": 284900}, {"word": "Soto", "value": 17700}, {"word": "Joey Chestnut", "value": 60400}, {"word": "Bieber", "value": 25400}, {"word": "Liberia", "value": 19100}, {"word": "#Zaporizhzhia", "value": 12000}, {"word": "Reparations", "value": 30600}, {"word": "Curb", "value": 11200}, {"word": "Trout", "value": 12500}, {"word": "Jungkook", "value": 11}, {"word": "Unilever", "value": 10300}, {"word": "ZNPP", "value": 16000}, {"word": "Secret Service", "value": 62400}, {"word": "Disinformation", "value": 26000}, {"word": "west wing", "value": 44700}], "url_map": {"Happy 4th": "http://twitter.com/search?q=Happy%204th", "Bol Bol": "http://twitter.com/search?q=Bol%20Bol", "White House": "http://twitter.com/search?q=White%20House", "Guatemala": "http://twitter.com/search?q=Guatemala", "Jerry": "http://twitter.com/search?q=Jerry", "Fourth of July": "http://twitter.com/search?q=Fourth%20of%20July", "Mingyu": "http://twitter.com/search?q=Mingyu", "Soto": "http://twitter.com/search?q=Soto", "Joey Chestnut": "http://twitter.com/search?q=Joey%20Chestnut", "Bieber": "http://twitter.com/search?q=Bieber", "Liberia": "http://twitter.com/search?q=Liberia", "#Zaporizhzhia": "http://twitter.com/search?q=%23Zaporizhzhia", "Reparations": "http://twitter.com/search?q=Reparations", "Curb": "http://twitter.com/search?q=Curb", "Trout": "http://twitter.com/search?q=Trout", "Jungkook": "http://twitter.com/search?q=Jungkook", "Unilever": "http://twitter.com/search?q=Unilever", "ZNPP": "http://twitter.com/search?q=ZNPP", "Secret Service": "http://twitter.com/search?q=Secret%20Service", "Disinformation": "http://twitter.com/search?q=Disinformation", "west wing": "http://twitter.com/search?q=west%20wing"}, "title": "Pop Tags", "topic": "USA"}