{"data": [{"word": "#LeMans24", "value": 35004}, {"word": "Garth", "value": 29359}, {"word": "Good Saturday", "value": 31227}, {"word": "Suchwita", "value": 134614}, {"word": "Can I Live", "value": 28410}, {"word": "Fang Fang", "value": 19471}, {"word": "Swiatek", "value": 10669}, {"word": "Nelly", "value": 10083}, {"word": "Coronel", "value": 165460}, {"word": "Bale", "value": 34355}, {"word": "Presidential Records Act", "value": 52866}, {"word": "Kid Rock", "value": 21251}, {"word": "Inter Milan", "value": 98105}, {"word": "Man City", "value": 107782}, {"word": "Emefiele", "value": 143084}, {"word": "Alts", "value": 123679}, {"word": "TODAY IS THE DAY", "value": 49760}, {"word": "Saliba", "value": 31469}, {"word": "Manchester City", "value": 100498}, {"word": "Blockbuster", "value": 15970}, {"word": "The PRA", "value": 18345}, {"word": "Bragg", "value": 15161}, {"word": "Clinton and Biden", "value": 39513}, {"word": "Nunes", "value": 10474}, {"word": "Hilda", "value": 87367}], "url_map": {"#LeMans24": "http://twitter.com/search?q=%23LeMans24", "Garth": "http://twitter.com/search?q=Garth", "Good Saturday": "http://twitter.com/search?q=%22Good+Saturday%22", "Suchwita": "http://twitter.com/search?q=Suchwita", "Can I Live": "http://twitter.com/search?q=%22Can+I+Live%22", "Fang Fang": "http://twitter.com/search?q=%22Fang+Fang%22", "Swiatek": "http://twitter.com/search?q=Swiatek", "Nelly": "http://twitter.com/search?q=Nelly", "Coronel": "http://twitter.com/search?q=Coronel", "Bale": "http://twitter.com/search?q=Bale", "Presidential Records Act": "http://twitter.com/search?q=%22Presidential+Records+Act%22", "Kid Rock": "http://twitter.com/search?q=%22Kid+Rock%22", "Inter Milan": "http://twitter.com/search?q=%22Inter+Milan%22", "Man City": "http://twitter.com/search?q=%22Man+City%22", "Emefiele": "http://twitter.com/search?q=Emefiele", "Alts": "http://twitter.com/search?q=Alts", "TODAY IS THE DAY": "http://twitter.com/search?q=%22TODAY+IS+THE+DAY%22", "Saliba": "http://twitter.com/search?q=Saliba", "Manchester City": "http://twitter.com/search?q=%22Manchester+City%22", "Blockbuster": "http://twitter.com/search?q=Blockbuster", "The PRA": "http://twitter.com/search?q=%22The+PRA%22", "Bragg": "http://twitter.com/search?q=Bragg", "Clinton and Biden": "http://twitter.com/search?q=%22Clinton+and+Biden%22", "Nunes": "http://twitter.com/search?q=Nunes", "Hilda": "http://twitter.com/search?q=Hilda"}, "title": "Pop Tags", "topic": "USA"}