{"data": [{"word": "Lakers", "value": 143500}, {"word": "#SmackDown", "value": 50100}, {"word": "Rich Paul", "value": 30700}, {"word": "Gabe Vincent", "value": 38800}, {"word": "Cam Reddish", "value": 22500}, {"word": "Derrick Rose", "value": 11400}, {"word": "Dennis", "value": 45800}, {"word": "Rockets", "value": 42400}, {"word": "Fred VanVleet", "value": 23500}, {"word": "Reaves", "value": 19700}, {"word": "Canelo", "value": 28000}, {"word": "ESPN", "value": 242300}, {"word": "Raptors", "value": 21300}, {"word": "The Braves", "value": 16900}, {"word": "López", "value": 138400}, {"word": "Kyrie", "value": 71500}, {"word": "Nimona", "value": 50300}, {"word": "Mavs", "value": 21700}, {"word": "Sohee", "value": 19900}, {"word": "LA Knight", "value": 12900}, {"word": "Charlo", "value": 11800}, {"word": "Schroder", "value": 13100}, {"word": "Jerami Grant", "value": 12400}, {"word": "Macron", "value": 460800}, {"word": "Strus", "value": 15800}, {"word": "Chapman", "value": 17000}], "url_map": {"Lakers": "http://twitter.com/search?q=Lakers", "#SmackDown": "http://twitter.com/search?q=%23SmackDown", "Rich Paul": "http://twitter.com/search?q=Rich%20Paul", "Gabe Vincent": "http://twitter.com/search?q=Gabe%20Vincent", "Cam Reddish": "http://twitter.com/search?q=Cam%20Reddish", "Derrick Rose": "http://twitter.com/search?q=Derrick%20Rose", "Dennis": "http://twitter.com/search?q=Dennis", "Rockets": "http://twitter.com/search?q=Rockets", "Fred VanVleet": "http://twitter.com/search?q=Fred%20VanVleet", "Reaves": "http://twitter.com/search?q=Reaves", "Canelo": "http://twitter.com/search?q=Canelo", "ESPN": "http://twitter.com/search?q=ESPN", "Raptors": "http://twitter.com/search?q=Raptors", "The Braves": "http://twitter.com/search?q=The%20Braves", "López": "http://twitter.com/search?q=L%C3%B3pez", "Kyrie": "http://twitter.com/search?q=Kyrie", "Nimona": "http://twitter.com/search?q=Nimona", "Mavs": "http://twitter.com/search?q=Mavs", "Sohee": "http://twitter.com/search?q=Sohee", "LA Knight": "http://twitter.com/search?q=LA%20Knight", "Charlo": "http://twitter.com/search?q=Charlo", "Schroder": "http://twitter.com/search?q=Schroder", "Jerami Grant": "http://twitter.com/search?q=Jerami%20Grant", "Macron": "http://twitter.com/search?q=Macron", "Strus": "http://twitter.com/search?q=Strus", "Chapman": "http://twitter.com/search?q=Chapman"}, "title": "Pop Tags", "topic": "USA"}