{"data": [{"word": "Balogun", "value": 22223}, {"word": "Durham", "value": 858577}, {"word": "Ledger", "value": 78483}, {"word": "#主的祈祷", "value": 427418}, {"word": "Hillary", "value": 259811}, {"word": "Francis", "value": 66154}, {"word": "Good Tuesday", "value": 35274}, {"word": "Magneto", "value": 33701}, {"word": "The FBI", "value": 695748}, {"word": "Mueller", "value": 73828}, {"word": "Comey", "value": 113264}, {"word": "Judge", "value": 161346}, {"word": "Treason", "value": 153919}, {"word": "Sports Illustrated", "value": 26504}, {"word": "McCabe", "value": 27943}, {"word": "Watergate", "value": 31394}, {"word": "Black Pink", "value": 277526}, {"word": "Jonah", "value": 16055}, {"word": "Rudy Giuliani", "value": 114626}, {"word": "Rockets", "value": 24350}, {"word": "Patriot", "value": 130438}, {"word": "JUST ANNOUNCED", "value": 22034}, {"word": "Russian Collusion", "value": 95789}, {"word": "Dwight", "value": 30476}, {"word": "Kinzhal", "value": 33231}], "url_map": {"Balogun": "http://twitter.com/search?q=Balogun", "Durham": "http://twitter.com/search?q=Durham", "Ledger": "http://twitter.com/search?q=Ledger", "#主的祈祷": "http://twitter.com/search?q=%23%E4%B8%BB%E7%9A%84%E7%A5%88%E7%A5%B7", "Hillary": "http://twitter.com/search?q=Hillary", "Francis": "http://twitter.com/search?q=Francis", "Good Tuesday": "http://twitter.com/search?q=%22Good+Tuesday%22", "Magneto": "http://twitter.com/search?q=Magneto", "The FBI": "http://twitter.com/search?q=%22The+FBI%22", "Mueller": "http://twitter.com/search?q=Mueller", "Comey": "http://twitter.com/search?q=Comey", "Judge": "http://twitter.com/search?q=Judge", "Treason": "http://twitter.com/search?q=Treason", "Sports Illustrated": "http://twitter.com/search?q=%22Sports+Illustrated%22", "McCabe": "http://twitter.com/search?q=McCabe", "Watergate": "http://twitter.com/search?q=Watergate", "Black Pink": "http://twitter.com/search?q=%22Black+Pink%22", "Jonah": "http://twitter.com/search?q=Jonah", "Rudy Giuliani": "http://twitter.com/search?q=%22Rudy+Giuliani%22", "Rockets": "http://twitter.com/search?q=Rockets", "Patriot": "http://twitter.com/search?q=Patriot", "JUST ANNOUNCED": "http://twitter.com/search?q=%22JUST+ANNOUNCED%22", "Russian Collusion": "http://twitter.com/search?q=%22Russian+Collusion%22", "Dwight": "http://twitter.com/search?q=Dwight", "Kinzhal": "http://twitter.com/search?q=Kinzhal"}, "title": "Pop Tags", "topic": "USA"}