{"data": [{"word": "#Pepeki", "value": 26177}, {"word": "Durham", "value": 31525}, {"word": "Miller Lite", "value": 19275}, {"word": "Curtis Jones", "value": 10778}, {"word": "got7", "value": 89574}, {"word": "Leicester", "value": 76809}, {"word": "#LEILIV", "value": 24167}, {"word": "Trump-Russia", "value": 21010}, {"word": "JUST ANNOUNCED", "value": 63589}, {"word": "Fairfax", "value": 15220}, {"word": "Vice", "value": 113788}, {"word": "Nakba", "value": 82192}, {"word": "White Out", "value": 41513}, {"word": "Kwon", "value": 13730}], "url_map": {"#Pepeki": "http://twitter.com/search?q=%23Pepeki", "Durham": "http://twitter.com/search?q=Durham", "Miller Lite": "http://twitter.com/search?q=%22Miller+Lite%22", "Curtis Jones": "http://twitter.com/search?q=%22Curtis+Jones%22", "got7": "http://twitter.com/search?q=got7", "Leicester": "http://twitter.com/search?q=Leicester", "#LEILIV": "http://twitter.com/search?q=%23LEILIV", "Trump-Russia": "http://twitter.com/search?q=Trump-Russia", "JUST ANNOUNCED": "http://twitter.com/search?q=%22JUST+ANNOUNCED%22", "Fairfax": "http://twitter.com/search?q=Fairfax", "Vice": "http://twitter.com/search?q=Vice", "Nakba": "http://twitter.com/search?q=Nakba", "White Out": "http://twitter.com/search?q=%22White+Out%22", "Kwon": "http://twitter.com/search?q=Kwon"}, "title": "Pop Tags", "topic": "USA"}